kraken_decompressor/__init__.py
kraken_decompressor/kraken_decompressor.cpython-311-x86_64-linux-musl.so
kraken_decompressor/kraken_decompressor.pyi
kraken_decompressor/py.typed
kraken_decompressor.libs/libgcc_s-0cd532bd.so.1
kraken_decompressor.libs/libstdc++-5d72f927.so.6.0.33
kraken_decompressor-0.2.1.dist-info/LICENSE
kraken_decompressor-0.2.1.dist-info/METADATA
kraken_decompressor-0.2.1.dist-info/WHEEL
kraken_decompressor-0.2.1.dist-info/RECORD
kraken_decompressor-0.2.1.dist-info/sboms/auditwheel.cdx.json
