Metadata-Version: 2.1
Name: kraken-decompressor
Version: 0.2.1
Summary: Oodle/Kraken decompressor.
Author: Powzix
Author-Email: Dominic Davis-Foster <dominic@davis-foster.co.uk>
License:                     GNU GENERAL PUBLIC LICENSE
Classifier: License :: OSI Approved :: GNU General Public License v3 (GPLv3)
Classifier: Operating System :: Microsoft :: Windows
Classifier: Operating System :: POSIX :: Linux
Classifier: Programming Language :: Python
Classifier: Programming Language :: Python :: 3 :: Only
Classifier: Programming Language :: Python :: 3.10
Classifier: Programming Language :: Python :: 3.11
Classifier: Programming Language :: Python :: 3.12
Classifier: Programming Language :: Python :: Implementation :: CPython
Project-URL: Homepage, https://github.com/domdfcoding/kraken-decompressor
Project-URL: Issue Tracker, https://github.com/domdfcoding/kraken-decompressor/issues
Project-URL: Source Code, https://github.com/domdfcoding/kraken-decompressor
Requires-Python: >=3.10
